[{"id":"1","lastname":"De La bas","firstname":"Julietta","email":"julia.jacob06@gmail.com","password":"azerty","children":"1","diet":"1","aliments":"patatexxxxxx","musique":"Destiny Childs","rsvpFr":"0","rsvpMa":"1","rsvpVin":"1","invitFr":"0","invitVin":"1","invitMa":"1","bachelor":"0","bachelorette":"0","admin":"1","marie":"0","seat":"60","ChildLastname1":"choubibou","ChildFirstname1":"bidouxxxxx","ChildLastname2":"dudu","ChildFirstname2":"didou","ChildLastname3":"frip","ChildFirstname3":"fripouille"},{"id":"2","lastname":"julia","firstname":"julia","email":"julia.jacob@hotmail.fr","password":"freferfsd","children":"0","diet":"0","aliments":"","musique":"","rsvpFr":"0","rsvpMa":"0","rsvpVin":"0","invitFr":"1","invitVin":"0","invitMa":"0","bachelor":"1","bachelorette":"0","admin":"0","marie":"0","seat":"12","ChildLastname1":"","ChildFirstname1":"","ChildLastname2":"","ChildFirstname2":"","ChildLastname3":"","ChildFirstname3":""},{"id":"3","lastname":"adriana","firstname":"adriana","email":"julia.jacob06@gmail.com","password":"azerty","children":"0","diet":"1","aliments":"j'aime pas les courgettes","musique":"","rsvpFr":"1","rsvpMa":"1","rsvpVin":"0","invitFr":"0","invitVin":"0","invitMa":"1","bachelor":"0","bachelorette":"0","admin":"0","marie":"0","seat":"46","ChildLastname1":"","ChildFirstname1":"","ChildLastname2":"","ChildFirstname2":"","ChildLastname3":"","ChildFirstname3":""},{"id":"4","lastname":"Durand","firstname":"Martin","email":"antony.mootoosamy@hotmail.fr","password":"azerty","children":"0","diet":"1","aliments":"je veux des bonbons","musique":"","rsvpFr":"0","rsvpMa":"1","rsvpVin":"0","invitFr":"0","invitVin":"0","invitMa":"1","bachelor":"0","bachelorette":"0","admin":"0","marie":"0","seat":"36","ChildLastname1":"","ChildFirstname1":"","ChildLastname2":"","ChildFirstname2":"","ChildLastname3":"","ChildFirstname3":""},{"id":"5","lastname":"Dupont","firstname":"Martin","email":"julia.jacob@hotmail.fr","password":"martin","children":"1","diet":"1","aliments":"v\u00e9g\u00e9tarien","musique":"","rsvpFr":"0","rsvpMa":"0","rsvpVin":"0","invitFr":"1","invitVin":"0","invitMa":"0","bachelor":"0","bachelorette":"0","admin":"0","marie":"0","seat":"42","ChildLastname1":"","ChildFirstname1":"","ChildLastname2":"","ChildFirstname2":"","ChildLastname3":"","ChildFirstname3":""},{"id":"6","lastname":"Green","firstname":"Rachel","email":"","password":"rachel","children":"0","diet":"1","aliments":"allergique aux langoustines","musique":"","rsvpFr":"1","rsvpMa":"1","rsvpVin":"0","invitFr":"1","invitVin":"0","invitMa":"1","bachelor":"1","bachelorette":"1","admin":"0","marie":"0","seat":"38","ChildLastname1":"","ChildFirstname1":"","ChildLastname2":"","ChildFirstname2":"","ChildLastname3":"","ChildFirstname3":""},{"id":"7","lastname":"Gueller","firstname":"Ross","email":"","password":"ross","children":"0","diet":"0","aliments":"","musique":"","rsvpFr":"1","rsvpMa":"0","rsvpVin":"0","invitFr":"0","invitVin":"0","invitMa":"0","bachelor":"0","bachelorette":"0","admin":"0","marie":"0","seat":"20","ChildLastname1":"","ChildFirstname1":"","ChildLastname2":"","ChildFirstname2":"","ChildLastname3":"","ChildFirstname3":""},{"id":"8","lastname":"Bing","firstname":"Chandler","email":"chandler.bing@gmail.fr","password":"azerty","children":"0","diet":"1","aliments":"courgettes","musique":"","rsvpFr":"1","rsvpMa":"1","rsvpVin":"0","invitFr":"1","invitVin":"1","invitMa":"1","bachelor":"1","bachelorette":"0","admin":"0","marie":"1","seat":"33","ChildLastname1":"","ChildFirstname1":"","ChildLastname2":"","ChildFirstname2":"","ChildLastname3":"","ChildFirstname3":""},{"id":"9","lastname":"Gueller","firstname":"Monica","email":"","password":"","children":"0","diet":"0","aliments":"","musique":"","rsvpFr":"0","rsvpMa":"0","rsvpVin":"0","invitFr":"0","invitVin":"0","invitMa":"0","bachelor":"0","bachelorette":"0","admin":"0","marie":"0","seat":"49","ChildLastname1":"","ChildFirstname1":"","ChildLastname2":"","ChildFirstname2":"","ChildLastname3":"","ChildFirstname3":""},{"id":"10","lastname":"gainsbourg","firstname":"serge","email":"","password":"azerty","children":"0","diet":"1","aliments":"pommes de terres","musique":"","rsvpFr":"0","rsvpMa":"1","rsvpVin":"0","invitFr":"1","invitVin":"0","invitMa":"1","bachelor":"0","bachelorette":"0","admin":"0","marie":"0","seat":"4","ChildLastname1":"","ChildFirstname1":"","ChildLastname2":"","ChildFirstname2":"","ChildLastname3":"","ChildFirstname3":""},{"id":"11","lastname":"de beauvoir","firstname":"simone","email":"","password":"azerty","children":"0","diet":"0","aliments":"","musique":"","rsvpFr":"1","rsvpMa":"0","rsvpVin":"0","invitFr":"1","invitVin":"0","invitMa":"1","bachelor":"0","bachelorette":"0","admin":"0","marie":"0","seat":"10","ChildLastname1":"","ChildFirstname1":"","ChildLastname2":"","ChildFirstname2":"","ChildLastname3":"","ChildFirstname3":""},{"id":"13","lastname":"Barse","firstname":"Alexandra","email":"","password":"azerty","children":"0","diet":"1","aliments":"mes allergies","musique":"","rsvpFr":"0","rsvpMa":"1","rsvpVin":"0","invitFr":"0","invitVin":"0","invitMa":"0","bachelor":"0","bachelorette":"0","admin":"0","marie":"0","seat":"0","ChildLastname1":"","ChildFirstname1":"","ChildLastname2":"","ChildFirstname2":"","ChildLastname3":"","ChildFirstname3":""},{"id":"14","lastname":"Mootoosamy","firstname":"Antony","email":"mootoosamy@gmail.fr","password":"cool","children":"1","diet":"1","aliments":"sky","musique":"","rsvpFr":"0","rsvpMa":"1","rsvpVin":"0","invitFr":"1","invitVin":"0","invitMa":"1","bachelor":"0","bachelorette":"0","admin":"0","marie":"0","seat":"0","ChildLastname1":"mootoosamy","ChildFirstname1":"lily","ChildLastname2":"motoosamy","ChildFirstname2":"noa","ChildLastname3":"smith","ChildFirstname3":"jaden"},{"id":"15","lastname":"jacob","firstname":"lucy","email":"lucy@hotmail.fr","password":"azerty","children":"0","diet":"1","aliments":"patatesss","musique":"","rsvpFr":"0","rsvpMa":"0","rsvpVin":"1","invitFr":"0","invitVin":"1","invitMa":"0","bachelor":"0","bachelorette":"0","admin":"0","marie":"0","seat":"0","ChildLastname1":"","ChildFirstname1":"","ChildLastname2":"","ChildFirstname2":"","ChildLastname3":"","ChildFirstname3":""},{"id":"20","lastname":"tex","firstname":"chaussette","email":"etstrsd@feds.fr","password":"frqs","children":"0","diet":"1","aliments":"teqsdwx","musique":"","rsvpFr":"0","rsvpMa":"0","rsvpVin":"0","invitFr":"1","invitVin":"0","invitMa":"0","bachelor":"0","bachelorette":"0","admin":"0","marie":"0","seat":"54","ChildLastname1":"","ChildFirstname1":"","ChildLastname2":"","ChildFirstname2":"","ChildLastname3":"","ChildFirstname3":""},{"id":"21","lastname":"1000","firstname":"acerola","email":"","password":"","children":"0","diet":"0","aliments":"","musique":"","rsvpFr":"0","rsvpMa":"0","rsvpVin":"0","invitFr":"0","invitVin":"0","invitMa":"0","bachelor":"0","bachelorette":"0","admin":"0","marie":"0","seat":"25","ChildLastname1":"","ChildFirstname1":"","ChildLastname2":"","ChildFirstname2":"","ChildLastname3":"","ChildFirstname3":""},{"id":"22","lastname":"Vie","firstname":"Science","email":"","password":"","children":"0","diet":"0","aliments":"","musique":"","rsvpFr":"0","rsvpMa":"0","rsvpVin":"0","invitFr":"1","invitVin":"1","invitMa":"0","bachelor":"0","bachelorette":"0","admin":"0","marie":"0","seat":"1","ChildLastname1":"","ChildFirstname1":"","ChildLastname2":"","ChildFirstname2":"","ChildLastname3":"","ChildFirstname3":""}]